tkui/__init__.py
tkui/base.py
tkui/layout.py
tkui/tkui.py
tkui/utils.py
TkUI-0.2.0.dist-info/LICENSE
TkUI-0.2.0.dist-info/METADATA
TkUI-0.2.0.dist-info/WHEEL
TkUI-0.2.0.dist-info/top_level.txt
TkUI-0.2.0.dist-info/RECORD
