Metadata-Version: 2.1
Name: TkUI
Version: 0.2.0
Summary: TkUI,是基于tkinter的Canvas模块开发的,具有现代化风格的UI库
Home-page: https://gitee.com/iamxcd/tk-ui
Author: iamxcd
Author-email: iamxcd@gmail.com
License-File: LICENSE
